testcontainers_spicedb/__init__.py
testcontainers_spicedb/spicedb.py
testcontainers_spicedb/testdata/__init__.py
testcontainers_spicedb-0.1.3.dist-info/licenses/LICENSE
testcontainers_spicedb-0.1.3.dist-info/METADATA
testcontainers_spicedb-0.1.3.dist-info/WHEEL
testcontainers_spicedb-0.1.3.dist-info/top_level.txt
testcontainers_spicedb-0.1.3.dist-info/RECORD
