Metadata-Version: 2.4
Name: testcontainers-spicedb
Version: 0.1.3
Summary: Python module for Testcontainers that provides a SpiceDB container for integration testing.
Author-email: Sohan Maheshwar <sohan.maheshwar@authzed.com>
Project-URL: Homepage, https://github.com/sohanmaheshwar/testcontainers-spicedb-py
Project-URL: Documentation, https://github.com/sohanmaheshwar/testcontainers-spicedb-py#readme
Project-URL: Repository, https://github.com/sohanmaheshwar/testcontainers-spicedb-py
Project-URL: Issues, https://github.com/sohanmaheshwar/testcontainers-spicedb-py/issues
Keywords: testcontainers,spicedb,testing
Classifier: Development Status :: 3 - Alpha
Classifier: Intended Audience :: Developers
Classifier: License :: OSI Approved :: MIT License
Classifier: Programming Language :: Python :: 3
Classifier: Programming Language :: Python :: 3.10
Classifier: Programming Language :: Python :: 3.11
Classifier: Programming Language :: Python :: 3.12
Requires-Python: >=3.10
License-File: LICENSE
Requires-Dist: testcontainers>=4.0.0
Requires-Dist: authzed>=0.10.0
Requires-Dist: grpcio>=1.50.0
Provides-Extra: dev
Requires-Dist: pytest>=7.0.0; extra == "dev"
Requires-Dist: pytest-asyncio>=0.21.0; extra == "dev"
Dynamic: license-file
